sandbox/__init__.py
sandbox/docker.py
sandbox/runner.py
sandbox/subprocess.py
sandbox_sdk-0.0.0.dist-info/METADATA
sandbox_sdk-0.0.0.dist-info/WHEEL
sandbox_sdk-0.0.0.dist-info/licenses/LICENSE
sandbox_sdk-0.0.0.dist-info/RECORD
