Metadata-Version: 2.4
Name: sandbox-sdk
Version: 0.0.0
Summary: Python Sandbox SDK
Project-URL: Homepage, https://mirascope.com/sandbox
Project-URL: Documentation, https://docs.mirascope.com/sandbox
Project-URL: Repository, https://github.com/Mirascope/sandbox
Project-URL: Issues, https://github.com/Mirascope/sandbox/issues
Project-URL: Changelog, https://github.com/Mirascope/sandbox/releases
Author-email: William Bakst <william@mirascope.com>
Maintainer-email: William Bakst <william@mirascope.com>
License:                                  Apache License
License-File: LICENSE
Keywords: sandbox
Classifier: Development Status :: 3 - Alpha
Classifier: Intended Audience :: Developers
Classifier: License :: OSI Approved :: MIT License
Classifier: Programming Language :: Python :: 3
Classifier: Programming Language :: Python :: 3.10
Classifier: Programming Language :: Python :: 3.11
Classifier: Programming Language :: Python :: 3.12
Classifier: Programming Language :: Python :: 3.13
Classifier: Topic :: Scientific/Engineering :: Artificial Intelligence
Classifier: Topic :: Software Development :: Libraries
Requires-Python: >=3.10
Provides-Extra: docker
Requires-Dist: docker>=7.1.0; extra == 'docker'
